todoclist/__init__.py
todoclist/scripts/__init__.py
todoclist/scripts/todoclist.py
todoclist-0.5.0.dist-info/entry_points.txt
todoclist-0.5.0.dist-info/METADATA
todoclist-0.5.0.dist-info/WHEEL
todoclist-0.5.0.dist-info/RECORD
