Metadata-Version: 2.1
Name: todoclist
Version: 0.5.0
Summary: 
Author: Ruslan Gagushin
Author-email: gagushin2@gmail.com
Requires-Python: >=3.12,<4.0
Classifier: Programming Language :: Python :: 3
Classifier: Programming Language :: Python :: 3.12
Requires-Dist: datetime (>=5.5,<6.0)
Requires-Dist: rich (>=13.7.1,<14.0.0)
Requires-Dist: todoist-api-python (>=2.1.4,<3.0.0)
Requires-Dist: typer (>=0.12.3,<0.13.0)
